MatplotlibHuituMijiChuyi/README.md
MatplotlibHuituMijiChuyi/__init__.py
MatplotlibHuituMijiChuyi/__main__.py
MatplotlibHuituMijiChuyi/file.epub
MatplotlibHuituMijiChuyi/index.html
MatplotlibHuituMijiChuyi/css/__init__.py
MatplotlibHuituMijiChuyi/css/annotations.css
MatplotlibHuituMijiChuyi/css/main.css
MatplotlibHuituMijiChuyi/css/normalize.css
MatplotlibHuituMijiChuyi/css/popup.css
MatplotlibHuituMijiChuyi/font/__init__.py
MatplotlibHuituMijiChuyi/font/fontello.eot
MatplotlibHuituMijiChuyi/font/fontello.svg
MatplotlibHuituMijiChuyi/font/fontello.ttf
MatplotlibHuituMijiChuyi/font/fontello.woff
MatplotlibHuituMijiChuyi/img/__init__.py
MatplotlibHuituMijiChuyi/img/annotator-glyph-sprite.png
MatplotlibHuituMijiChuyi/img/annotator-icon-sprite.png
MatplotlibHuituMijiChuyi/img/apple-touch-icon.png
MatplotlibHuituMijiChuyi/img/cancelfullscreen.png
MatplotlibHuituMijiChuyi/img/close.png
MatplotlibHuituMijiChuyi/img/fullscreen.png
MatplotlibHuituMijiChuyi/img/loader.gif
MatplotlibHuituMijiChuyi/img/menu-icon.png
MatplotlibHuituMijiChuyi/img/save.png
MatplotlibHuituMijiChuyi/img/saved.png
MatplotlibHuituMijiChuyi/img/settings-s.png
MatplotlibHuituMijiChuyi/img/settings.png
MatplotlibHuituMijiChuyi/img/star.png
MatplotlibHuituMijiChuyi/js/__init__.py
MatplotlibHuituMijiChuyi/js/epub.js
MatplotlibHuituMijiChuyi/js/epub.min.js
MatplotlibHuituMijiChuyi/js/epub.min.map
MatplotlibHuituMijiChuyi/js/hooks.min.js
MatplotlibHuituMijiChuyi/js/hooks.min.map
MatplotlibHuituMijiChuyi/js/reader.js
MatplotlibHuituMijiChuyi/js/reader.js.map
MatplotlibHuituMijiChuyi/js/reader.min.js
MatplotlibHuituMijiChuyi/js/reader.min.map
MatplotlibHuituMijiChuyi/js/hooks/__init__.py
MatplotlibHuituMijiChuyi/js/hooks/extensions/__init__.py
MatplotlibHuituMijiChuyi/js/hooks/extensions/highlight.js
MatplotlibHuituMijiChuyi/js/libs/__init__.py
MatplotlibHuituMijiChuyi/js/libs/jquery.min.js
MatplotlibHuituMijiChuyi/js/libs/localforage.min.js
MatplotlibHuituMijiChuyi/js/libs/screenfull.js
matplotlib_huitu_miji_chuyi-2024.3.5.0.dist-info/METADATA
matplotlib_huitu_miji_chuyi-2024.3.5.0.dist-info/WHEEL
matplotlib_huitu_miji_chuyi-2024.3.5.0.dist-info/entry_points.txt
matplotlib_huitu_miji_chuyi-2024.3.5.0.dist-info/top_level.txt
matplotlib_huitu_miji_chuyi-2024.3.5.0.dist-info/RECORD
